smart_scraping_agent/__init__.py
smart_scraping_agent/custom_json_parser.py
smart_scraping_agent/llm_friendly_loader.py
smart_scraping_agent/prompt_factory.py
smart_scraping_agent/smart_scraper.py
smart_scraping_agent/utils.py
smart_scraping_agent-0.0.10.dist-info/LICENSE
smart_scraping_agent-0.0.10.dist-info/METADATA
smart_scraping_agent-0.0.10.dist-info/WHEEL
smart_scraping_agent-0.0.10.dist-info/top_level.txt
smart_scraping_agent-0.0.10.dist-info/RECORD
