Metadata-Version: 2.2
Name: smart-scraping-agent
Version: 0.0.10
Summary: Autonomous Scraping Agent: Scrape URLs with prompts and schema
Author-email: Rohan Dhanraj Yadav <rohan.aigroup@gmail.com>
License: MIT License
Project-URL: Homepage, https://github.com/rohan-aigroup/smart_scraper_package
Project-URL: Issues, https://github.com/rohan-aigroup/smart_scraper_package/issues
Classifier: Programming Language :: Python :: 3
Classifier: Operating System :: OS Independent
Requires-Python: >=3.12
License-File: LICENSE
Requires-Dist: fastapi
Requires-Dist: langchain
Requires-Dist: langchain-community
Requires-Dist: langchain-core
Requires-Dist: langchain-openai
Requires-Dist: langchain-text-splitters
Requires-Dist: markdownify
Requires-Dist: playwright
Requires-Dist: python-dotenv
